[
  {
    "job_id": 1,
    "tanggal_posting": "14/01/2019",
    "contact": "Naufal Rajabi",
    "perekrut": 181511023,
    "title": "Android developer",
    "description": "Persyaratan Umum :\n\n-Pria\n-Muslim\n-Jujur,Pekerja keras,Amanah\n- Mampu bekerja Team\n-Berkomunikasi dengan Baik.\n-Pas Foto terbaru 4 x 6 : 2 L\n-Surat keterangan berbadan Sehat\n-Surat kelakuan baik\n-Bersedia Ditempatkan di JAKARTA TIMUR\n\n# Persyaratan Khusus\n\n- S1 System Information Universitas Terkemuka\n-Usia Max 35\n-Mampu bekerja dengan target\n-Diutamakan yg berpengalaman minimal 1 tahun sebagai android developer\n- Jenis kerjaan : Full-time\n- Memahami konsep pemograman OOP\n- Menguasai JavaScript, Java, SQL\n- Berpengalaman menggunakan database MySQL\n- Menguasai PHP, CSS, HTML 5 adalah poin plus\n- Menguasai grafis design adalah poin plus",
    "quantity": 1,
    "jobType": 1,
    "location": "Jakarta Timur",
    "endDate": null,
    "benefits": null,
    "duration": null,
    "companyName": null,
    "remote": false,
    "minSalary": null,
    "maxSalary": null,
    "descriptionAddition": "Diutamakan yg berpengalaman minimal 1 tahun sebagai android developer\nS1 System Information Universitas Terkemuka",
    "genderReq": 1,
    "religionReq": 1,
    "studyProgramReq": null,
    "skills_req": [
      "JavaScript",
      "Java (programming language)",
      "SQL",
      "MySQL",
      "PHP",
      "CSS",
      "HTML"
    ]
  },
  {
    "job_id": 2,
    "tanggal_posting": "01/02/2019",
    "contact": "Alifia Syalsabila",
    "perekrut": 171511003,
    "title": "Android developer",
    "description": "1. Muslim/Muslimah\n2. Tidak merokok\n3. Usia maksimal 35 tahun\n4. Pendidikan terakhir minimal D3 untuk posisi No.1,SMK untuk posisi no 2 & 3\n5. Pengalaman min. 1 tahun dibidangnya\n6. Fresh Graduate welcome",
    "quantity": 1,
    "jobType": 1,
    "location": null,
    "endDate": null,
    "benefits": null,
    "duration": null,
    "companyName": null,
    "remote": false,
    "minSalary": null,
    "maxSalary": null,
    "descriptionAddition": "Pendidikan terakhir minimal D3 untuk posisi No.1,SMK untuk posisi no 2 & 3",
    "genderReq": null,
    "religionReq": null,
    "studyProgramReq": null,
    "skills_req": [
      "Android software development"
    ]
  },
  {
    "job_id": 3,
    "tanggal_posting": "01/02/2019",
    "contact": "Alifia Syalsabila",
    "perekrut": 171511003,
    "title": "Ios developer",
    "description": "1. Muslim/Muslimah\n2. Tidak merokok\n3. Usia maksimal 35 tahun\n4. Pendidikan terakhir minimal D3 untuk posisi No.1,SMK untuk posisi no 2 & 3\n5. Pengalaman min. 1 tahun dibidangnya\n6. Fresh Graduate welcome",
    "quantity": 1,
    "jobType": 1,
    "location": null,
    "endDate": null,
    "benefits": null,
    "duration": null,
    "companyName": null,
    "remote": false,
    "minSalary": null,
    "maxSalary": null,
    "descriptionAddition": "Pendidikan terakhir minimal D3 untuk posisi No.1,SMK untuk posisi no 2 & 3",
    "genderReq": null,
    "religionReq": null,
    "studyProgramReq": null,
    "skills_req": [
      "IOS development software"
    ]
  },
  {
    "job_id": 4,
    "tanggal_posting": "10/02/2019",
    "contact": "Lisnawati",
    "perekrut": 171511018,
    "title": "Web developer",
    "description": "Yang bisa laravel",
    "quantity": 1,
    "jobType": 2,
    "location": null,
    "endDate": null,
    "benefits": null,
    "duration": null,
    "companyName": null,
    "remote": true,
    "minSalary": null,
    "maxSalary": null,
    "descriptionAddition": null,
    "genderReq": null,
    "religionReq": null,
    "studyProgramReq": null,
    "skills_req": [
      "Web development",
      "Laravel"
    ]
  },
  {
    "job_id": 5,
    "tanggal_posting": "20/02/2019",
    "contact": "Reka Alamsyah",
    "perekrut": 151511029,
    "title": "Web developer",
    "description": "2 orang di web laravel",
    "quantity": 2,
    "jobType": 2,
    "location": null,
    "endDate": null,
    "benefits": null,
    "duration": null,
    "companyName": null,
    "remote": true,
    "minSalary": null,
    "maxSalary": null,
    "descriptionAddition": null,
    "genderReq": null,
    "religionReq": null,
    "studyProgramReq": null,
    "skills_req": [
      "Web development",
      "Laravel"
    ]
  },
  {
    "job_id": 6,
    "tanggal_posting": "20/02/2019",
    "contact": "Reka Alamsyah",
    "perekrut": 151511029,
    "title": "Android developer",
    "description": "2 orang di mobile android",
    "quantity": 2,
    "jobType": 2,
    "location": null,
    "endDate": null,
    "benefits": null,
    "duration": null,
    "companyName": null,
    "remote": true,
    "minSalary": null,
    "maxSalary": null,
    "descriptionAddition": null,
    "genderReq": null,
    "religionReq": null,
    "studyProgramReq": null,
    "skills_req": [
      "Android software development"
    ]
  },
  {
    "job_id": 7,
    "tanggal_posting": "11/05/2019",
    "contact": "Debora Eirene",
    "perekrut": 161511007,
    "title": "Web developer",
    "description": "Website sederhana dari jurusan administrasi niaga",
    "quantity": 1,
    "jobType": 2,
    "location": null,
    "endDate": null,
    "benefits": null,
    "duration": null,
    "companyName": null,
    "remote": true,
    "minSalary": null,
    "maxSalary": null,
    "descriptionAddition": null,
    "genderReq": null,
    "religionReq": null,
    "studyProgramReq": null,
    "skills_req": [
      "Web development"
    ]
  },
  {
    "job_id": 8,
    "tanggal_posting": "19/05/2019",
    "contact": "Omeeeeeennn",
    "perekrut": 151511027,
    "title": "Web developer",
    "description": "Web simpel menggunakan bahasa apa aja",
    "quantity": 1,
    "jobType": 2,
    "location": null,
    "endDate": null,
    "benefits": null,
    "duration": null,
    "companyName": null,
    "remote": true,
    "minSalary": null,
    "maxSalary": null,
    "descriptionAddition": null,
    "genderReq": null,
    "religionReq": null,
    "studyProgramReq": null,
    "skills_req": [
      "Web development"
    ]
  },
  {
    "job_id": 9,
    "tanggal_posting": "21/06/2019",
    "contact": "Nikita Nabila",
    "perekrut": 171511024,
    "title": "Programmer",
    "description": "Persyaratan:\n- Pria Maks. 25 thn\n- Freshgraduate / Berpengalaman min. 1 Tahun\n- Pendidikan  S1 \n- Jurusan informatika\n- Jujur, teliti, tekun dan mampu bekerjasama\n- Mau untuk terus berkembang dan memiliki logika yang baik\n- Memahami dan mampu mengoperasikan delphi, SQL Server, dan MySQL\n- Memahami dan mampu membuat serta memantau website\n- Memahami PHP Framework, jQuery, Java, dan html5 menjadi nilai +\n- Memahami jaringan menjadi nilai +",
    "quantity": 1,
    "jobType": 1,
    "location": null,
    "endDate": null,
    "benefits": null,
    "duration": null,
    "companyName": null,
    "remote": false,
    "minSalary": null,
    "maxSalary": null,
    "descriptionAddition": "Freshgraduate / Berpengalaman min. 1 Tahun\nPendidikan  S1 \nJurusan informatika",
    "genderReq": null,
    "religionReq": null,
    "studyProgramReq": null,
    "skills_req": [
      "Web development",
      "MySQL",
      "Microsoft SQL Server",
      "PHP",
      "JQuery",
      "Java (programming language)",
      "HTML",
      "Zend Framework",
      "Laravel",
      "CodeIgniter",
      "Phalcon (framework)"
    ]
  },
  {
    "job_id": 10,
    "tanggal_posting": "05/08/2019",
    "contact": "Bening",
    "perekrut": 181511006,
    "title": "Programmer",
    "description": "Skill database (query oracle)",
    "quantity": 1,
    "jobType": 1,
    "location": null,
    "endDate": null,
    "benefits": null,
    "duration": null,
    "companyName": null,
    "remote": false,
    "minSalary": null,
    "maxSalary": null,
    "descriptionAddition": null,
    "genderReq": null,
    "religionReq": null,
    "studyProgramReq": null,
    "skills_req": [
      "Oracle Database"
    ]
  },
  {
    "job_id": 11,
    "tanggal_posting": "13/08/2019",
    "contact": "Nikita Nabila",
    "perekrut": 171511024,
    "title": "Web developer",
    "description": "Crud sama search, disuahakan bukan mahasiswa yang lagi KP/PKL",
    "quantity": 1,
    "jobType": 2,
    "location": null,
    "endDate": null,
    "benefits": null,
    "duration": null,
    "companyName": null,
    "remote": true,
    "minSalary": null,
    "maxSalary": null,
    "descriptionAddition": null,
    "genderReq": null,
    "religionReq": null,
    "studyProgramReq": null,
    "skills_req": [
      "Web development"
    ]
  },
  {
    "job_id": 12,
    "tanggal_posting": "15/09/2019",
    "contact": "yogsss",
    "perekrut": 171511037,
    "title": "iOS, Android, Front-End, SDET, Back-End Developer",
    "description": "1. iOS:\nSwift & ObjC\n\n2. Android\nJava & Kotlin\n\n3. Front-End\nJavascript & HTML\n\n4. SDET\nJava\n\n5. Back-End Developer\nJava, Spring, & Spring Boot Technology",
    "quantity": 1,
    "jobType": 1,
    "location": null,
    "endDate": null,
    "benefits": null,
    "duration": null,
    "companyName": null,
    "remote": false,
    "minSalary": null,
    "maxSalary": null,
    "descriptionAddition": null,
    "genderReq": null,
    "religionReq": null,
    "studyProgramReq": null,
    "skills_req": [
      "Swift (programming language)",
      "Java (programming language)",
      "Kotlin (programming language)",
      "JavaScript",
      "HTML"
    ]
  },
  {
    "job_id": 13,
    "tanggal_posting": "27/09/2019",
    "contact": "Rezky WS",
    "perekrut": 181511031,
    "title": "Software Engineer",
    "description": "* Bachelor degree in Computer Science, Information System, Information Technology, Software Engineering and Electrical Engineering, Math, Physics from Reputable Universities\n* Experiences in Java or C/C++ programming languages\n* Experiences or software construction and unit test\n* Strong understanding on mobile and web technologies\n* Strong understanding logic, algorithm, and data structure concepts",
    "quantity": 1,
    "jobType": 1,
    "location": null,
    "endDate": null,
    "benefits": null,
    "duration": null,
    "companyName": null,
    "remote": false,
    "minSalary": null,
    "maxSalary": null,
    "descriptionAddition": "Bachelor degree in Computer Science, Information System, Information Technology, Software Engineering and Electrical Engineering, Math, Physics from Reputable Universities",
    "genderReq": null,
    "religionReq": null,
    "studyProgramReq": null,
    "skills_req": [
      "Java (programming language)",
      "C (programming language)",
      "C++"
    ]
  },
  {
    "job_id": 14,
    "tanggal_posting": "28/10/2019",
    "contact": "Jays",
    "perekrut": 171511016,
    "title": "Project Manager, System Analyst, Front End, Back End, Quality Assurance",
    "description": "- Mengerti bahasa pemrograman PHP\n- Mengerti dan pernah menggunakan minimal satu framework PHP\n- Dapat diminta untuk mempelajari framework phalcon PHP",
    "quantity": 1,
    "jobType": 2,
    "location": null,
    "endDate": null,
    "benefits": null,
    "duration": null,
    "companyName": null,
    "remote": true,
    "minSalary": null,
    "maxSalary": null,
    "descriptionAddition": null,
    "genderReq": null,
    "religionReq": null,
    "studyProgramReq": null,
    "skills_req": [
      "PHP",
      "Phalcon (framework)",
      "Laravel",
      "CodeIgniter",
      "Zend Framework"
    ]
  },
  {
    "job_id": 15,
    "tanggal_posting": "20/11/2019",
    "contact": "Alif Ramdani",
    "perekrut": 171511002,
    "title": "Computer Vision & Data Science",
    "description": "Bahasa Python",
    "quantity": 1,
    "jobType": 1,
    "location": null,
    "endDate": null,
    "benefits": null,
    "duration": null,
    "companyName": null,
    "remote": false,
    "minSalary": null,
    "maxSalary": null,
    "descriptionAddition": null,
    "genderReq": null,
    "religionReq": null,
    "studyProgramReq": null,
    "skills_req": [
      "Python (programming language)"
    ]
  },
  {
    "job_id": 16,
    "tanggal_posting": "15/01/2019",
    "contact": "Reka Alamsyah R.",
    "perekrut": 151511029,
    "title": "Web developer",
    "description": "Minimal pernah pake react atau vue js, dan laravel",
    "quantity": 1,
    "jobType": 1,
    "location": null,
    "endDate": null,
    "benefits": null,
    "duration": null,
    "companyName": null,
    "remote": false,
    "minSalary": null,
    "maxSalary": null,
    "descriptionAddition": null,
    "genderReq": null,
    "religionReq": null,
    "studyProgramReq": null,
    "skills_req": [
      "React Native",
      "Vue.js",
      "Laravel"
    ]
  },
  {
    "job_id": 17,
    "tanggal_posting": "20/03/2020",
    "contact": "Nikita Nabila",
    "perekrut": 171511024,
    "title": "Web Developer",
    "description": "* Proven working experience as a Web Developer at least 2 year\n* Fresh graduate or other education background with strong willingness to learn are welcome\n* Having extensive knowledge on PHP, PostgreSQL, HTML5, CSS3, Javascript and Responsive Web Design\n* Familiar with PHP framewoek such as Laravel\n* Familiar (and not limited to) with framewoek and library such as bootstrap and jQuery\n* Knowledge of: css pre processor such as LESS/SCSS. Having knowledge of SEO is a plus\n* Knowledge of: GIT version control system\n* Strong analytical and problem solving skills\n* Able to working full-time and on site in Bandung",
    "quantity": 1,
    "jobType": 1,
    "location": "Bandung",
    "endDate": null,
    "benefits": null,
    "duration": null,
    "companyName": null,
    "remote": false,
    "minSalary": null,
    "maxSalary": null,
    "descriptionAddition": "Proven working experience as a Web Developer at least 2 year\nFresh graduate or other education background with strong willingness to learn are welcome",
    "genderReq": null,
    "religionReq": null,
    "studyProgramReq": null,
    "skills_req": [
      "Web development",
      "PHP",
      "HTML",
      "CSS",
      "JavaScript",
      "PostgreSQL",
      "Laravel",
      "JQuery",
      "Bootstrap (front-end framework)",
      "Git"
    ]
  },
  {
    "job_id": 18,
    "tanggal_posting": "21/04/2020",
    "contact": "Nadia Pd",
    "perekrut": 181511022,
    "title": "Software Developer",
    "description": "Kualifikasi Utama:\n1. Menguasai bahasa programming phyton\n\nKualifikasi Tambahan:\n1. Menguasai program C++ (level basic)\n2. Memiliki dasar frontend untuk pembuatan desain GUI\n3. Memahami database MySQL\n4. Pernah memiliki project berkaitan dengan Raspberry Pi is a plus",
    "quantity": 1,
    "jobType": 1,
    "location": null,
    "endDate": null,
    "benefits": null,
    "duration": null,
    "companyName": null,
    "remote": false,
    "minSalary": null,
    "maxSalary": null,
    "descriptionAddition": null,
    "genderReq": null,
    "religionReq": null,
    "studyProgramReq": null,
    "skills_req": [
      "Python (programming language)",
      "C++",
      "MySQL",
      "Raspberry Pi OS"
    ]
  },
  {
    "job_id": 19,
    "tanggal_posting": "04/06/2020",
    "contact": "Rohmat Dasuki",
    "perekrut": 161511033,
    "title": "Programmer",
    "description": "Angular dan Laravel",
    "quantity": 1,
    "jobType": 1,
    "location": null,
    "endDate": null,
    "benefits": null,
    "duration": null,
    "companyName": null,
    "remote": false,
    "minSalary": null,
    "maxSalary": null,
    "descriptionAddition": null,
    "genderReq": null,
    "religionReq": null,
    "studyProgramReq": null,
    "skills_req": [
      "AngularJS",
      "Laravel"
    ]
  },
  {
    "job_id": 20,
    "tanggal_posting": "20/07/2020",
    "contact": "Hendra Permana",
    "perekrut": 161511010,
    "title": "Programmer",
    "description": "1. Berpengalaman pada Socket Programming\n2. Menguasai bahasa Pemrograman Java/Python menjadi nilai tambah",
    "quantity": 1,
    "jobType": 1,
    "location": null,
    "endDate": null,
    "benefits": null,
    "duration": null,
    "companyName": null,
    "remote": false,
    "minSalary": null,
    "maxSalary": null,
    "descriptionAddition": null,
    "genderReq": null,
    "religionReq": null,
    "studyProgramReq": null,
    "skills_req": [
      "Java (programming language)",
      "Python (programming language)"
    ]
  },
  {
    "job_id": 21,
    "tanggal_posting": "05/08/2020",
    "contact": "ikhsans",
    "perekrut": 181511012,
    "title": "Web Developer",
    "description": "assalamualaikum\ndicari web developer rate diatas umr,\nlulusan SMK/D3,\ntertarik harap email ke rizal@pindad.com\nnuhun",
    "quantity": 1,
    "jobType": 1,
    "location": null,
    "endDate": null,
    "benefits": null,
    "duration": null,
    "companyName": null,
    "remote": false,
    "minSalary": null,
    "maxSalary": null,
    "descriptionAddition": "lulusan SMK/D3",
    "genderReq": null,
    "religionReq": null,
    "studyProgramReq": null,
    "skills_req": [
      "Web development"
    ]
  },
  {
    "job_id": 22,
    "tanggal_posting": "28/08/2020",
    "contact": "Jays",
    "perekrut": 171511016,
    "title": "Web Developer",
    "description": "Diutamakan Vue.js developer",
    "quantity": "2-4",
    "jobType": 2,
    "location": null,
    "endDate": null,
    "benefits": null,
    "duration": null,
    "companyName": null,
    "remote": true,
    "minSalary": null,
    "maxSalary": null,
    "descriptionAddition": null,
    "genderReq": null,
    "religionReq": null,
    "studyProgramReq": null,
    "skills_req": [
      "Web development",
      "Vue.js"
    ]
  },
  {
    "job_id": 23,
    "tanggal_posting": "14/09/2020",
    "contact": "Lisa",
    "perekrut": 181511017,
    "title": "Web Developer",
    "description": "Assalamualaikum, punten di sini ada yg bisa bikin web virtual 3d event?\nuntuk liat sample nya, bisa pc dlu. Hatur nuhun",
    "quantity": 1,
    "jobType": 2,
    "location": null,
    "endDate": null,
    "benefits": null,
    "duration": null,
    "companyName": null,
    "remote": true,
    "minSalary": null,
    "maxSalary": null,
    "descriptionAddition": null,
    "genderReq": null,
    "religionReq": null,
    "studyProgramReq": null,
    "skills_req": [
      "Web development"
    ]
  },
  {
    "job_id": 24,
    "tanggal_posting": "19/09/2020",
    "contact": "Reynaldy Rizky S.",
    "perekrut": 191511030,
    "title": "Anggota Tim PKM-M",
    "description": "Assalamu'alaikum. Kami (Fauzan, Marissa, dan Rey dari kelas D4-2A) sedang mencari anggota tim untuk PKM-M dengan syarat mahasiswa prodi D3 angkatan 2019 atau mahasiswa angkatan 2018/2017. Topik PKM adalah Sistem Pendeteksi Kecelakaan Mobil. Bagi yang berminat silahkan menghubungi saya. Terima kasih",
    "quantity": 1,
    "jobType": 2,
    "location": null,
    "endDate": null,
    "benefits": null,
    "duration": null,
    "companyName": null,
    "remote": false,
    "minSalary": null,
    "maxSalary": null,
    "descriptionAddition": null,
    "genderReq": null,
    "religionReq": null,
    "studyProgramReq": null,
    "skills_req": []
  },
  {
    "job_id": 25,
    "tanggal_posting": "12/10/2020",
    "contact": "Afif",
    "perekrut": 171511001,
    "title": "Programmer",
    "description": "Flutter, CI",
    "quantity": 1,
    "jobType": 2,
    "location": null,
    "endDate": null,
    "benefits": null,
    "duration": null,
    "companyName": null,
    "remote": true,
    "minSalary": null,
    "maxSalary": null,
    "descriptionAddition": null,
    "genderReq": null,
    "religionReq": null,
    "studyProgramReq": null,
    "skills_req": [
      "Flutter (software)",
      "CodeIgniter"
    ]
  },
  {
    "job_id": 26,
    "tanggal_posting": "19/10/2020",
    "contact": "Lisa",
    "perekrut": 181511017,
    "title": "Programmer Web",
    "description": "1. Terbiasa (mengerti dan menguasi) php 5 dan mysql, minimal menggunakan selama 1 tahun\n2. Menguasai HTML, CSS, dan JavaScript\n3. Menguasai framework CI dan bootstrap \n4. Bersedia bekerja cepat\n\n⭐️jujur dan dapat dipercaya",
    "quantity": 1,
    "jobType": 1,
    "location": null,
    "endDate": null,
    "benefits": null,
    "duration": null,
    "companyName": null,
    "remote": false,
    "minSalary": null,
    "maxSalary": null,
    "descriptionAddition": "Terbiasa (mengerti dan menguasi) php 5 dan mysql, minimal menggunakan selama 1 tahun",
    "genderReq": null,
    "religionReq": null,
    "studyProgramReq": null,
    "skills_req": [
      "Web development",
      "PHP",
      "MySQL",
      "HTML",
      "CSS",
      "JavaScript",
      "CodeIgniter",
      "Bootstrap (front-end framework)"
    ]
  },
  {
    "job_id": 27,
    "tanggal_posting": "19/10/2020",
    "contact": "Lisa",
    "perekrut": 181511017,
    "title": "Android developer",
    "description": "Project android atau odoo",
    "quantity": 1,
    "jobType": 2,
    "location": null,
    "endDate": null,
    "benefits": null,
    "duration": null,
    "companyName": null,
    "remote": true,
    "minSalary": null,
    "maxSalary": null,
    "descriptionAddition": null,
    "genderReq": null,
    "religionReq": null,
    "studyProgramReq": null,
    "skills_req": [
      "Android software development"
    ]
  },
  {
    "job_id": 28,
    "tanggal_posting": "27/10/2020",
    "contact": "yogsss",
    "perekrut": 171511037,
    "title": "Web Developer dan Mobile Developer",
    "description": "PT. Sanghiang Perkasa (Kalbe Nutritionals) database:\n\n Web Developer:\n- Min. S1 Teknologi Informatika, Ilmu Komputer, dan jurusan sejenis lainnya\n- Memiliki pengalaman minimal 2 tahun sebagai Web Developer (full-stack)\n- Menguasai bahasa pemrograman .Net (mvc)\n- Mampu bekerja secara multi-tasking\n\nMobile Developer:\n- Min. S1 Teknologi Informatika, Ilmu Komputer, dan jurusan sejenis lainnya\n- Memiliki pengalaman minimal 2 tahun sebagai Mobile Developer (full-stack)\n- Menguasai Android Studio\n- Mampu bekerja secara multi-tasking\n\nSilakan mengirimkan CV terupdate Anda ke ervita.komala@kalbenutritionals.com. Terima kasih",
    "quantity": 2,
    "jobType": 1,
    "location": "Karawang, Jawa Barat",
    "endDate": null,
    "benefits": null,
    "duration": null,
    "companyName": "PT. Sanghiang Perkasa",
    "remote": false,
    "minSalary": null,
    "maxSalary": null,
    "descriptionAddition": "Min. S1 Teknologi Informatika, Ilmu Komputer, dan jurusan sejenis lainnya\nMemiliki pengalaman minimal 2 tahun sebagai Web Developer (full-stack)\nMemiliki pengalaman minimal 2 tahun sebagai Mobile Developer (full-stack)",
    "genderReq": null,
    "religionReq": null,
    "studyProgramReq": null,
    "skills_req": [
      "Web development",
      "Android software development",
      ".NET Framework",
      "Android Studio"
    ]
  },
  {
    "job_id": 29,
    "tanggal_posting": "28/10/2020",
    "contact": "Hilmy Okto",
    "perekrut": 181511011,
    "title": "Unity Multiplayer Developer",
    "description": "PENGUMUMAN....\nBagi Sobat Hantu yang mau bergabung dengan Lentera Nusantara sebagai Unity Multiplayer Developer, bisa kirim CV dan Portofolio ke admin@lentera-nusantara.com\nMimin tunggu yaaaa... 😉\nmaksimal sampai tanggal 30 November 2020\nSEMANGAT! 💪😎\n\n#ghostparadegame #ghostparade #bandung #lowongan #lowongankerja #game #gamebandung #gamekonsol #konsolgame #comics #ghostparadecomic #loker #lokerbandung #lokerprogrammer\n#videogames\n#bausastralelembut\n#gamedeveloper\n#GhostParade #GhostParadeGame #Numskull\n#NumskullGames #Switch #Gaming\n#komikinajah \n#aksysgames",
    "quantity": 1,
    "jobType": 1,
    "location": "Bandung",
    "endDate": "30/11/2020",
    "benefits": null,
    "duration": null,
    "companyName": "Lentera Nusantara",
    "remote": false,
    "minSalary": null,
    "maxSalary": null,
    "descriptionAddition": null,
    "genderReq": null,
    "religionReq": null,
    "studyProgramReq": null,
    "skills_req": [
      "Unity (game engine)"
    ]
  },
  {
    "job_id": 30,
    "tanggal_posting": "28/10/2020",
    "contact": "Jays",
    "perekrut": 171511016,
    "title": "Senior Developer",
    "description": "Info lowongan PT. Infomedia Nusantara:\n\nDibutuhkan segera untuk posisi Senior Developer dengan kriteria sbb:\n\n1. Pria/Wanita, Min Pendidikan S1/D3\n2. Basic Java\n3. Database Oracle, MySQL\n4. Development colaboration (jenkins, Github, Jira)\n5. Linux/Unix\n6. Basic Kubernetes\n7. Stay 1 year during project\n\nBenefit:\n- Salary\n- BPJS\n\nPenempatan di Gedung Telkomsel Smart Office, Gatot Subroto, Jakarta (Untuk saat ini WFH)",
    "quantity": 1,
    "jobType": 1,
    "location": "Jakarta",
    "endDate": null,
    "benefits": "- Salary\n- BPJS",
    "duration": null,
    "companyName": null,
    "remote": true,
    "minSalary": null,
    "maxSalary": null,
    "descriptionAddition": "Min Pendidikan S1/D3\nStay 1 year during project",
    "genderReq": null,
    "religionReq": null,
    "studyProgramReq": null,
    "skills_req": [
      "Java (programming language)",
      "Oracle Database",
      "MySQL",
      "Kubernetes"
    ]
  },
  {
    "job_id": 31,
    "tanggal_posting": "29/10/2020",
    "contact": "Andi Fauzy",
    "perekrut": 181511005,
    "title": "Project Manager",
    "description": "Ada project nih temen\". Pengerjaan satu bulan, requirement :\n1. React Native\n2. Redux-saga, \nFee bisa didiskusikan, yang minat boleh pc saya, buat dihubungi ke orang pemilik project. Hatur nuhun 🙏",
    "quantity": 1,
    "jobType": 2,
    "location": null,
    "endDate": null,
    "benefits": null,
    "duration": "1 bulan",
    "companyName": null,
    "remote": true,
    "minSalary": null,
    "maxSalary": null,
    "descriptionAddition": null,
    "genderReq": null,
    "religionReq": null,
    "studyProgramReq": null,
    "skills_req": [
      "React Native",
      "Redux (JavaScript library)"
    ]
  },
  {
    "job_id": 32,
    "tanggal_posting": "06/11/2020",
    "contact": "Mumuh KMuharam",
    "perekrut": 171511021,
    "title": "PHP Programmer",
    "description": "Neuronworks\nMale/Max 30yo\nDomicile/Assigned on Bandung\nRequired maximal for S1 Information System\nAlready accustomed about PHP Programming, php, Zend, Laravel, & CI in Framework, Proficient in MySQL Database programming, php, oracle programming, html, css, bootstrap & javascript programming.\n3 years expreience in programming\nvery good on manage database design.\nGood attitude and be able to work with team",
    "quantity": 1,
    "jobType": 1,
    "location": "Bandung",
    "endDate": null,
    "benefits": null,
    "duration": null,
    "companyName": null,
    "remote": false,
    "minSalary": null,
    "maxSalary": null,
    "descriptionAddition": "3 years expreience in programming\nRequired maximal for S1 Information System",
    "genderReq": null,
    "religionReq": null,
    "studyProgramReq": null,
    "skills_req": [
      "PHP",
      "Zend Framework",
      "Laravel",
      "CodeIgniter",
      "MySQL",
      "Oracle Database",
      "HTML",
      "CSS",
      "JavaScript",
      "Bootstrap (front-end framework)"
    ]
  },
  {
    "job_id": 33,
    "tanggal_posting": "11/11/2020",
    "contact": "Ivan Eka",
    "perekrut": 181511049,
    "title": "Mobile Developer",
    "description": "Android and IOS\nSalary 4,5jt - 7 jt",
    "quantity": 1,
    "jobType": 1,
    "location": null,
    "endDate": null,
    "benefits": null,
    "duration": null,
    "companyName": null,
    "remote": false,
    "minSalary": 4500000,
    "maxSalary": 7000000,
    "descriptionAddition": null,
    "genderReq": null,
    "religionReq": null,
    "studyProgramReq": null,
    "skills_req": [
      "IOS development software",
      "Android software development"
    ]
  },
  {
    "job_id": 34,
    "tanggal_posting": "11/11/2020",
    "contact": "Norman Ibrahim S",
    "perekrut": 171511025,
    "title": "Java Web Programmer",
    "description": "[ INFO LOKER PROGRAMMER JAVA ]\n\nBismillah, mau menginformasikan, ada lowongan pekerjaan di bidang programmer web java, s.d. 10 orang\nTempat : onsite, di bank BUMN Jakarta\nSalary : sesuai hasil test (pasti diatas UMR)\n\nyang berminat bisa hubungi norman\natau email aja ke nibrahimsultan@gmail.com\n\nTerima kasih",
    "quantity": 10,
    "jobType": 1,
    "location": "Jakarta",
    "endDate": null,
    "benefits": null,
    "duration": null,
    "companyName": "Bank BUMN Jakarta",
    "remote": false,
    "minSalary": null,
    "maxSalary": null,
    "descriptionAddition": null,
    "genderReq": null,
    "religionReq": null,
    "studyProgramReq": null,
    "skills_req": [
      "Web development",
      "Java (programming language)"
    ]
  },
  {
    "job_id": 35,
    "tanggal_posting": "04/12/2020",
    "contact": "Rhio",
    "perekrut": 181511064,
    "title": "Fullstack Developer dan Front End Developer",
    "description": "1. Memiliki gelar di bidang Ilmu Komputer, Teknik Informatika, Sistem Informasi atau jurusan terkait.\n2. Memiliki pengalaman kerja di bidang tersebut min. 1 tahun\n3. Mampu melakukan pengembangan pada halaman web & pengkodean untuk pemeliharaan aset digital perusahaan\n4. Menguasai PHP (Native of Frameworks), HTML, CSS, JS Framework (Angular, React, dll), dan familiar dengan CMS terutama Wordpress\n5. Familiar dengan API integration seperti Rest API\n6. Lokasi kantor: Pointlab Coworking Space, Graha Pos Indonesia, Jl. Banda No.30,Bandung",
    "quantity": 1,
    "jobType": 1,
    "location": "Bandung",
    "endDate": null,
    "benefits": null,
    "duration": null,
    "companyName": null,
    "remote": false,
    "minSalary": null,
    "maxSalary": null,
    "descriptionAddition": "Memiliki gelar di bidang Ilmu Komputer, Teknik Informatika, Sistem Informasi atau jurusan terkait.\nMemiliki pengalaman kerja di bidang tersebut min. 1 tahun",
    "genderReq": null,
    "religionReq": null,
    "studyProgramReq": null,
    "skills_req": [
      "Web development",
      "PHP",
      "HTML",
      "CSS",
      "JavaScript",
      "AngularJS",
      "Vue.js",
      "React Native",
      "WordPress"
    ]
  }
]